{
  "schema": "config_v1",
  "generated": 1779106123429,
  "endpoints": [
    "/T93YzE",
    "/2gAK2cCH"
  ],
  "limits": {
    "min": 8,
    "max": 3275
  },
  "jJhaBa": 46693,
  "WWxqo": "YKXSAFZtsuPv",
  "2njfJX": 30223,
  "eGnFz": "qKWFYy21XHFZ",
  "mVIxs3": 33799,
  "IMqXuV": 36478,
  "ZpyUvW": 46251,
  "omM3Jl": 35555,
  "UyGNI": "7vIWboJlJ2Ec",
  "N7d6xN": 14790,
  "zysF9V": 12037,
  "n0BzmD": 8457,
  "zZBW5": "u4pFnhyvLFGE",
  "MOFNyi": 31401,
  "aYToDX": 36701,
  "kMB5C": "yvoyWGKjm5Qo",
  "aHCnaF": 47162,
  "FXBspG": 46817,
  "qnjyr": "wHunoBjMk5Wy",
  "WAXVsp": 9837,
  "4rMim": "eHYpWd6bnshj",
  "9RaYJE": 31051,
  "gIBaaa": 47411,
  "NOgjW": "Mvr0a1CxalMS",
  "kaq5e1": 39377,
  "WNsYK": "KChRMw4td0L5",
  "1AFtFu": 31355,
  "fgIfM": "ePHcOMAtu0aT",
  "KYA3V1": 9521,
  "7pIGnV": 1525,
  "aVxIME": 37287,
  "8oVOiR": 7628,
  "yMK0Do": 28077,
  "cvDED": "SwPhkPeaA3fm",
  "TInFVF": 38786,
  "4p8p0v": 1518,
  "205Aj": "ieZ8vwbMW42V"
}
/* final checksum */ const CHECKSUM = 206995;
